src/__init__.py
src/_version.py
src/main.py
src/api/endpoints.py
src/api/metrics.py
src/api/middleware_integration.py
src/api/routers/__init__.py
src/api/routers/v1.py
src/api/services/__init__.py
src/api/services/key_rotation.py
src/api/services/provider_context.py
src/api/services/streaming.py
src/api/utils/yaml_formatter.py
src/cli/__init__.py
src/cli/main.py
src/cli/utils.py
src/cli/commands/__init__.py
src/cli/commands/config.py
src/cli/commands/health.py
src/cli/commands/models.py
src/cli/commands/server.py
src/cli/commands/test.py
src/cli/commands/wrap.py
src/cli/wrap/__init__.py
src/cli/wrap/proxy_manager.py
src/cli/wrap/wrappers.py
src/config/__init__.py
src/config/defaults.toml
src/conversion/anthropic_sse_to_openai.py
src/conversion/anthropic_to_openai.py
src/conversion/content_utils.py
src/conversion/conversion_metrics.py
src/conversion/errors.py
src/conversion/models_converter.py
src/conversion/openai_stream_to_claude_state_machine.py
src/conversion/openai_to_anthropic.py
src/conversion/request_converter.py
src/conversion/response_converter.py
src/conversion/tool_call_delta.py
src/conversion/tool_name_sanitizer.py
src/conversion/tool_schema.py
src/core/alias_config.py
src/core/alias_manager.py
src/core/anthropic_client.py
src/core/client.py
src/core/config.py
src/core/constants.py
src/core/logging.py
src/core/model_manager.py
src/core/provider_config.py
src/core/provider_manager.py
src/core/security.py
src/core/cache/disk.py
src/core/logging/__init__.py
src/core/logging/configuration.py
src/core/logging/conversation.py
src/core/logging/filters/http.py
src/core/logging/formatters/base.py
src/core/logging/formatters/correlation.py
src/core/logging/formatters/syslog.py
src/core/metrics/CLAUDE.md
src/core/metrics/__init__.py
src/core/metrics/runtime.py
src/core/metrics/types.py
src/core/metrics/calculations/accumulation.py
src/core/metrics/calculations/duration.py
src/core/metrics/calculations/hierarchical.py
src/core/metrics/models/__init__.py
vandamme_proxy-1.4.1.dist-info/METADATA
vandamme_proxy-1.4.1.dist-info/WHEEL
vandamme_proxy-1.4.1.dist-info/entry_points.txt
vandamme_proxy-1.4.1.dist-info/RECORD
