Metadata-Version: 2.4
Name: vandamme-proxy
Version: 1.4.1
Summary: A proxy server that converts Claude API requests to OpenAI-compatible API calls
Project-URL: Homepage, https://github.com/elifarley/vandamme-proxy
Project-URL: Repository, https://github.com/elifarley/vandamme-proxy.git
Project-URL: Issues, https://github.com/elifarley/vandamme-proxy/issues
Author-email: Vandamme Proxy <noreply@example.com>
Classifier: Development Status :: 4 - Beta
Classifier: Intended Audience :: Developers
Classifier: License :: OSI Approved :: MIT License
Classifier: Programming Language :: Python :: 3
Classifier: Programming Language :: Python :: 3.11
Classifier: Programming Language :: Python :: 3.12
Requires-Python: >=3.10
Requires-Dist: dash-ag-grid>=31.2.0
Requires-Dist: dash-bootstrap-components[cli]>=2.0.4
Requires-Dist: dash[cli]>=3.3.0
Requires-Dist: fastapi[standard]>=0.115.11
Requires-Dist: openai>=1.54.0
Requires-Dist: pydantic>=2.0.0
Requires-Dist: python-dotenv>=1.0.0
Requires-Dist: respx>=0.22.0
Requires-Dist: tomli>=2.0.0
Requires-Dist: uvicorn>=0.34.0
Provides-Extra: cli
Requires-Dist: pyyaml>=6.0; extra == 'cli'
Requires-Dist: rich>=13.0.0; extra == 'cli'
Requires-Dist: typer[all]>=0.9.0; extra == 'cli'
Provides-Extra: dev
Requires-Dist: httpx>=0.25.0; extra == 'dev'
Requires-Dist: pytest-asyncio>=0.21.0; extra == 'dev'
Requires-Dist: pytest>=7.0.0; extra == 'dev'
